devhelpers/__init__.py
devhelpers/__version__.py
devhelpers/isatomic.py
devhelpers/nogc.py
devhelpers/timeit.py
devhelpers-0.1.2.dist-info/LICENSE.txt
devhelpers-0.1.2.dist-info/WHEEL
devhelpers-0.1.2.dist-info/METADATA
devhelpers-0.1.2.dist-info/RECORD
