Metadata-Version: 2.1
Name: devhelpers
Version: 0.1.2
Summary: A Development Toolbox
Home-page: https://github.com/MichaelSasser/devhelpers
License: GPL-3.0-or-later
Keywords: devtools,development,tools
Author: Michael Sasser
Author-email: Michael@MichaelSasser.org
Maintainer: Michael Sasser
Maintainer-email: Michael@MichaelSasser.org
Requires-Python: >=3.9,<4.0
Classifier: Development Status :: 2 - Pre-Alpha
Classifier: Intended Audience :: Developers
Classifier: License :: OSI Approved :: GNU General Public License v3 or later (GPLv3+)
Classifier: Natural Language :: English
Classifier: Operating System :: OS Independent
Classifier: Programming Language :: Python :: 3
Classifier: Programming Language :: Python :: 3 :: Only
Classifier: Programming Language :: Python :: 3.9
Classifier: Topic :: Software Development
Classifier: Topic :: Software Development :: Libraries :: Python Modules
Classifier: Topic :: Software Development :: Quality Assurance
Classifier: Topic :: Software Development :: Testing
Classifier: Typing :: Typed
Provides-Extra: docs
Requires-Dist: Sphinx (>=3.5.1,<4.0.0); extra == "docs"
Requires-Dist: numpydoc (>=1.1.0,<2.0.0); extra == "docs"
Requires-Dist: sphinx-autodoc-typehints (>=1.11.1,<2.0.0); extra == "docs"
Project-URL: Documentation, https://michaelsasser.github.io/devhelpers/index.html
Project-URL: Repository, https://github.com/MichaelSasser/devhelpers
